outline_vpn_api_client/__init__.py
outline_vpn_api_client/__main__.py
outline_vpn_api_client/async_client.py
outline_vpn_api_client/client.py
outline_vpn_api_client/error.py
outline_vpn_api_client/models.py
outline_vpn_api_client-1.2.2.dist-info/LICENSE
outline_vpn_api_client-1.2.2.dist-info/METADATA
outline_vpn_api_client-1.2.2.dist-info/WHEEL
outline_vpn_api_client-1.2.2.dist-info/RECORD
