Metadata-Version: 2.1
Name: outline-vpn-api-client
Version: 1.2.2
Summary: 
Author: zeph1rr
Author-email: grianton535@gmail.com
Requires-Python: >=3.12,<4.0
Classifier: Programming Language :: Python :: 3
Classifier: Programming Language :: Python :: 3.12
Classifier: Programming Language :: Python :: 3.13
Provides-Extra: async
Requires-Dist: httpx[http2] (>=0.28.1,<0.29.0) ; extra == "async"
Requires-Dist: pydantic (>=2.10.4,<3.0.0)
Requires-Dist: requests (>=2.32.3,<3.0.0)
